Workbook

Sheet Início
A1: #VALUE!
E2: MAIS CONSULTORIA | IR | I2: ORGANIZAÇÃO • CLAREZA • CONTROLE
B6: VISÃO GERAL | IMPOSTO DE RENDA
A7: IMPOSTO DE RENDA | B7: Organize lançamentos, cadastre seus dados, reúna informes e acompanhe os totais em tempo real.
A9: =IFERROR(HYPERLINK("#'Início'!B10","INÍCIO"),"INÍCIO") -> INÍCIO | B9: Bem-vindo(a) à sua central de organização de IR | K9: ANO-CALENDÁRIO
K10: ANO-BASE → | L10: 2025
B11: Preencha as abas na ordem: 1. Transações → 2. Dados Pessoais → 3. Informes.
A12: =IFERROR(HYPERLINK("#'Transações'!B10","TRANSAÇÕES"),"TRANSAÇÕES") -> TRANSAÇÕES
A15: =IFERROR(HYPERLINK("#'Dados Pessoais'!B10","DADOS PESSOAIS"),"DADOS PESSOAIS") -> DADOS PESSOAIS | B15: RENDIMENTOS | E15: DESPESAS DEDUTÍVEIS | H15: OUTRAS DESPESAS | K15: INFORMES
B16: =SUMIFS(Transações!$F$12:$F$215,Transações!$C$12:$C$215,"Rendimento",Transações!$B$12:$B$215,">="&DATE($L$10,1,1),Transações!$B$12:$B$215,"<"&DATE($L$10+1,1,1)) -> 1615 | E16: =SUMIFS(Transações!$F$12:$F$215,Transações!$C$12:$C$215,"Despesa dedutível",Transações!$B$12:$B$215,">="&DATE($L$10,1,1),Transações!$B$12:$B$215,"<"&DATE($L$10+1,1,1)) -> 611 | H16: =SUMIFS(Transações!$F$12:$F$215,Transações!$C$12:$C$215,"Despesa não dedutível",Transações!$B$12:$B$215,">="&DATE($L$10,1,1),Transações!$B$12:$B$215,"<"&DATE($L$10+1,1,1)) -> 0 | K16: =COUNTIF(INFORMES!$B$12:$B$31,"?*") -> 1
A18: =IFERROR(HYPERLINK("#'INFORMES'!B10","INFORMES"),"INFORMES") -> INFORMES
B19: Receitas registradas | E19: Itens declarados como dedutíveis | H19: Despesas não dedutíveis | K19: Instituições com informe
A21: =IFERROR(HYPERLINK("#'Relatórios'!B10","RELATÓRIOS"),"RELATÓRIOS") -> RELATÓRIOS | B21: VISÃO GERAL • REGISTROS E PENDÊNCIAS
B23: Movimentações lançadas | F23: =COUNT(Transações!$F$12:$F$215) -> 3 | H23: Dados pessoais básicos | K23: =IF(AND('Dados Pessoais'!E10<>"",'Dados Pessoais'!E11<>"",'Dados Pessoais'!J18<>""),"Preenchidos","Pendentes") -> Pendentes
A28: Mais Consultoria
A29: Organização de IR

Sheet Transações
A1: #VALUE!
E2: MAIS CONSULTORIA | IR | I2: ORGANIZAÇÃO • CLAREZA • CONTROLE
B6: 1 | TRANSAÇÕES
A7: IMPOSTO DE RENDA | B7: Lance receitas, despesas e comprovantes. A ordem de preenchimento começa por esta aba.
A9: =IFERROR(HYPERLINK("#'Início'!B10","INÍCIO"),"INÍCIO") -> INÍCIO | B9: CADASTRO DE LANÇAMENTOS | J9: PAINEL DO ANO-BASE
B11: Data | C11: Tipo | D11: Categoria | E11: Descrição / fonte pagadora | F11: Valor (R$) | G11: CPF / CNPJ | H11: Comprovante / arquivo | I11: Revisão | J11: ANO-CALENDÁRIO
A12: =IFERROR(HYPERLINK("#'Transações'!B10","TRANSAÇÕES"),"TRANSAÇÕES") -> TRANSAÇÕES | B12: 45945 | C12: Rendimento | D12: CNPJ | E12: Aluguel recebido | F12: 1615 | G12: 123321123-32 | I12: Conferido | J12: =Início!L10 -> 2025
B13: 45946 | C13: Despesa dedutível | D13: CNPJ | E13: Só saude | F13: 465 | G13: 321123321-12 | I13: Falta comprovante
B14: 45658 | C14: Despesa dedutível | D14: CNPJ | E14: Dental | F14: 146 | G14: 345543435-34 | I14: Conferido
A15: =IFERROR(HYPERLINK("#'Dados Pessoais'!B10","DADOS PESSOAIS"),"DADOS PESSOAIS") -> DADOS PESSOAIS | J15: RECEITAS
J16: =Início!B16 -> 1615
A18: =IFERROR(HYPERLINK("#'INFORMES'!B10","INFORMES"),"INFORMES") -> INFORMES
J19: DEDUÇÕES INFORMADAS
J20: =Início!E16 -> 611
A21: =IFERROR(HYPERLINK("#'Relatórios'!B10","RELATÓRIOS"),"RELATÓRIOS") -> RELATÓRIOS
J23: OUTRAS DESPESAS
J24: =Início!H16 -> 0
A29: Mais Consultoria
A30: Organização de IR

Sheet Dados Pessoais
A1: #VALUE!
E2: MAIS CONSULTORIA | IR | I2: ORGANIZAÇÃO • CLAREZA • CONTROLE
B6: 2 | DADOS PESSOAIS
A7: IMPOSTO DE RENDA
B8: IDENTIFICAÇÃO DO CONTRIBUINTE | H8: ENDEREÇO E CONTATO
A9: =IFERROR(HYPERLINK("#'Início'!B10","INÍCIO"),"INÍCIO") -> INÍCIO
B10: NOME COMPLETO | H10: LOGRADOURO
B11: CPF (11 DÍGITOS) | E11: 01623456789 | H11: NÚMERO / COMPLEMENTO
A12: =IFERROR(HYPERLINK("#'Transações'!B10","TRANSAÇÕES"),"TRANSAÇÕES") -> TRANSAÇÕES | B12: DATA DE NASCIMENTO | H12: BAIRRO
B13: TÍTULO DE ELEITOR | H13: CIDADE
B14: ESTADO CIVIL | H14: UF
A15: =IFERROR(HYPERLINK("#'Dados Pessoais'!B10","DADOS PESSOAIS"),"DADOS PESSOAIS") -> DADOS PESSOAIS | B15: NOME DO CÔNJUGE | H15: CEP
B16: QUANTIDADE DE DEPENDENTES | H16: TELEFONE FIXO
B17: RESIDENTE NO EXTERIOR? | H17: CELULAR
A18: =IFERROR(HYPERLINK("#'INFORMES'!B10","INFORMES"),"INFORMES") -> INFORMES | B18: ALTEROU DADOS NO ANO ANTERIOR? | H18: E-MAIL
B19: OCUPAÇÃO PRINCIPAL | H19: INFORMES REUNIDOS?
B20: VALIDAÇÃO BÁSICA DE PREENCHIMENTO
A21: =IFERROR(HYPERLINK("#'Relatórios'!B10","RELATÓRIOS"),"RELATÓRIOS") -> RELATÓRIOS | B21: CPF (formato) | E21: =IF(E11="","Pendente",IF(LEN(SUBSTITUTE(SUBSTITUTE(E11,".",""),"-",""))=11,"11 dígitos informados","Revisar o CPF")) -> 11 dígitos informados
H22: DICAS PARA CONFERÊNCIA
B23: DEPENDENTES
B25: Nome do dependente | C25: CPF | D25: Vínculo | E25: Nascimento | G25: Informações complementares
A29: Mais Consultoria
A30: Organização de IR

Sheet INFORMES
A1: #VALUE!
E2: MAIS CONSULTORIA | IR | I2: ORGANIZAÇÃO • CLAREZA • CONTROLE
B6: 3 | INFORMES DE RENDIMENTOS
A7: IMPOSTO DE RENDA | B7: Controle informes de bancos, corretoras e outras fontes, com referência aos documentos.
A9: =IFERROR(HYPERLINK("#'Início'!B10","INÍCIO"),"INÍCIO") -> INÍCIO | B9: INFORMES BANCÁRIOS E DE RENDIMENTOS | J9: DADOS DO ANO-BASE
B11: Instituição / banco | C11: Tipo de informe | D11: CNPJ da fonte | E11: Ano-base | F11: Saldo em 31/12 (R$) | G11: Rendimentos (R$) | H11: Arquivo / referência | I11: Conferência | J11: =Início!L10 -> 2025
A12: =IFERROR(HYPERLINK("#'Transações'!B10","TRANSAÇÕES"),"TRANSAÇÕES") -> TRANSAÇÕES | B12: 218 - Banco Bonsucesso | C12: Investimentos | D12: 051237890001-19 | E12: 2025 | F12: 10000 | G12: 1213 | I12: Conferido
A15: =IFERROR(HYPERLINK("#'Dados Pessoais'!B10","DADOS PESSOAIS"),"DADOS PESSOAIS") -> DADOS PESSOAIS
J16: O saldo patrimonial e os rendimentos são informações distintas. Não some o saldo bancário à renda tributável.
A18: =IFERROR(HYPERLINK("#'INFORMES'!B10","INFORMES"),"INFORMES") -> INFORMES
A21: =IFERROR(HYPERLINK("#'Relatórios'!B10","RELATÓRIOS"),"RELATÓRIOS") -> RELATÓRIOS
J23: Associe cada informe ao PDF ou documento recebido da instituição. A classificação e a declaração definitivas dependem das regras oficiais.
A29: Mais Consultoria
A30: Organização de IR
B34: TOTAIS DE INSTITUIÇÕES / FONTES | F34: =SUM(F12:F31) -> 10000 | G34: =SUM(G12:G31) -> 1213 | H34: Valores informados

Sheet Relatórios
A1: #VALUE!
E2: MAIS CONSULTORIA | IR | I2: ORGANIZAÇÃO • CLAREZA • CONTROLE
B6: 4 | RELATÓRIOS
A7: IMPOSTO DE RENDA | B7: Resumo financeiro anual para conferência. Valores calculados automaticamente a partir de Transações.
A9: =IFERROR(HYPERLINK("#'Início'!B10","INÍCIO"),"INÍCIO") -> INÍCIO | B9: MOVIMENTAÇÃO MENSAL POR TIPO | H9: COMPARATIVO MENSAL
B11: Mês nº | C11: Mês | D11: Rendimentos (R$) | E11: Dedutíveis (R$) | F11: Não dedutíveis (R$) | G11: Diferença (R$)
A12: =IFERROR(HYPERLINK("#'Transações'!B10","TRANSAÇÕES"),"TRANSAÇÕES") -> TRANSAÇÕES | B12: 1 | C12: Janeiro | D12: =SUMIFS(Transações!$F$12:$F$215,Transações!$C$12:$C$215,"Rendimento",Transações!$B$12:$B$215,">="&DATE(Início!$L$10,$B12,1),Transações!$B$12:$B$215,"<"&EDATE(DATE(Início!$L$10,$B12,1),1)) -> 0 | E12: =SUMIFS(Transações!$F$12:$F$215,Transações!$C$12:$C$215,"Despesa dedutível",Transações!$B$12:$B$215,">="&DATE(Início!$L$10,$B12,1),Transações!$B$12:$B$215,"<"&EDATE(DATE(Início!$L$10,$B12,1),1)) -> 146 | F12: =SUMIFS(Transações!$F$12:$F$215,Transações!$C$12:$C$215,"Despesa não dedutível",Transações!$B$12:$B$215,">="&DATE(Início!$L$10,$B12,1),Transações!$B$12:$B$215,"<"&EDATE(DATE(Início!$L$10,$B12,1),1)) -> 0 | G12: =D12-E12-F12 -> -146
B13: 2 | C13: Fevereiro | D13: =SUMIFS(Transações!$F$12:$F$215,Transações!$C$12:$C$215,"Rendimento",Transações!$B$12:$B$215,">="&DATE(Início!$L$10,$B13,1),Transações!$B$12:$B$215,"<"&EDATE(DATE(Início!$L$10,$B13,1),1)) -> 0 | E13: =SUMIFS(Transações!$F$12:$F$215,Transações!$C$12:$C$215,"Despesa dedutível",Transações!$B$12:$B$215,">="&DATE(Início!$L$10,$B13,1),Transações!$B$12:$B$215,"<"&EDATE(DATE(Início!$L$10,$B13,1),1)) -> 0 | F13: =SUMIFS(Transações!$F$12:$F$215,Transações!$C$12:$C$215,"Despesa não dedutível",Transações!$B$12:$B$215,">="&DATE(Início!$L$10,$B13,1),Transações!$B$12:$B$215,"<"&EDATE(DATE(Início!$L$10,$B13,1),1)) -> 0 | G13: =D13-E13-F13 -> 0
B14: 3 | C14: Março | D14: =SUMIFS(Transações!$F$12:$F$215,Transações!$C$12:$C$215,"Rendimento",Transações!$B$12:$B$215,">="&DATE(Início!$L$10,$B14,1),Transações!$B$12:$B$215,"<"&EDATE(DATE(Início!$L$10,$B14,1),1)) -> 0 | E14: =SUMIFS(Transações!$F$12:$F$215,Transações!$C$12:$C$215,"Despesa dedutível",Transações!$B$12:$B$215,">="&DATE(Início!$L$10,$B14,1),Transações!$B$12:$B$215,"<"&EDATE(DATE(Início!$L$10,$B14,1),1)) -> 0 | F14: =SUMIFS(Transações!$F$12:$F$215,Transações!$C$12:$C$215,"Despesa não dedutível",Transações!$B$12:$B$215,">="&DATE(Início!$L$10,$B14,1),Transações!$B$12:$B$215,"<"&EDATE(DATE(Início!$L$10,$B14,1),1)) -> 0 | G14: =D14-E14-F14 -> 0
A15: =IFERROR(HYPERLINK("#'Dados Pessoais'!B10","DADOS PESSOAIS"),"DADOS PESSOAIS") -> DADOS PESSOAIS | B15: 4 | C15: Abril | D15: =SUMIFS(Transações!$F$12:$F$215,Transações!$C$12:$C$215,"Rendimento",Transações!$B$12:$B$215,">="&DATE(Início!$L$10,$B15,1),Transações!$B$12:$B$215,"<"&EDATE(DATE(Início!$L$10,$B15,1),1)) -> 0 | E15: =SUMIFS(Transações!$F$12:$F$215,Transações!$C$12:$C$215,"Despesa dedutível",Transações!$B$12:$B$215,">="&DATE(Início!$L$10,$B15,1),Transações!$B$12:$B$215,"<"&EDATE(DATE(Início!$L$10,$B15,1),1)) -> 0 | F15: =SUMIFS(Transações!$F$12:$F$215,Transações!$C$12:$C$215,"Despesa não dedutível",Transações!$B$12:$B$215,">="&DATE(Início!$L$10,$B15,1),Transações!$B$12:$B$215,"<"&EDATE(DATE(Início!$L$10,$B15,1),1)) -> 0 | G15: =D15-E15-F15 -> 0
B16: 5 | C16: Maio | D16: =SUMIFS(Transações!$F$12:$F$215,Transações!$C$12:$C$215,"Rendimento",Transações!$B$12:$B$215,">="&DATE(Início!$L$10,$B16,1),Transações!$B$12:$B$215,"<"&EDATE(DATE(Início!$L$10,$B16,1),1)) -> 0 | E16: =SUMIFS(Transações!$F$12:$F$215,Transações!$C$12:$C$215,"Despesa dedutível",Transações!$B$12:$B$215,">="&DATE(Início!$L$10,$B16,1),Transações!$B$12:$B$215,"<"&EDATE(DATE(Início!$L$10,$B16,1),1)) -> 0 | F16: =SUMIFS(Transações!$F$12:$F$215,Transações!$C$12:$C$215,"Despesa não dedutível",Transações!$B$12:$B$215,">="&DATE(Início!$L$10,$B16,1),Transações!$B$12:$B$215,"<"&EDATE(DATE(Início!$L$10,$B16,1),1)) -> 0 | G16: =D16-E16-F16 -> 0
B17: 6 | C17: Junho | D17: =SUMIFS(Transações!$F$12:$F$215,Transações!$C$12:$C$215,"Rendimento",Transações!$B$12:$B$215,">="&DATE(Início!$L$10,$B17,1),Transações!$B$12:$B$215,"<"&EDATE(DATE(Início!$L$10,$B17,1),1)) -> 0 | E17: =SUMIFS(Transações!$F$12:$F$215,Transações!$C$12:$C$215,"Despesa dedutível",Transações!$B$12:$B$215,">="&DATE(Início!$L$10,$B17,1),Transações!$B$12:$B$215,"<"&EDATE(DATE(Início!$L$10,$B17,1),1)) -> 0 | F17: =SUMIFS(Transações!$F$12:$F$215,Transações!$C$12:$C$215,"Despesa não dedutível",Transações!$B$12:$B$215,">="&DATE(Início!$L$10,$B17,1),Transações!$B$12:$B$215,"<"&EDATE(DATE(Início!$L$10,$B17,1),1)) -> 0 | G17: =D17-E17-F17 -> 0
A18: =IFERROR(HYPERLINK("#'INFORMES'!B10","INFORMES"),"INFORMES") -> INFORMES | B18: 7 | C18: Julho | D18: =SUMIFS(Transações!$F$12:$F$215,Transações!$C$12:$C$215,"Rendimento",Transações!$B$12:$B$215,">="&DATE(Início!$L$10,$B18,1),Transações!$B$12:$B$215,"<"&EDATE(DATE(Início!$L$10,$B18,1),1)) -> 0 | E18: =SUMIFS(Transações!$F$12:$F$215,Transações!$C$12:$C$215,"Despesa dedutível",Transações!$B$12:$B$215,">="&DATE(Início!$L$10,$B18,1),Transações!$B$12:$B$215,"<"&EDATE(DATE(Início!$L$10,$B18,1),1)) -> 0 | F18: =SUMIFS(Transações!$F$12:$F$215,Transações!$C$12:$C$215,"Despesa não dedutível",Transações!$B$12:$B$215,">="&DATE(Início!$L$10,$B18,1),Transações!$B$12:$B$215,"<"&EDATE(DATE(Início!$L$10,$B18,1),1)) -> 0 | G18: =D18-E18-F18 -> 0
B19: 8 | C19: Agosto | D19: =SUMIFS(Transações!$F$12:$F$215,Transações!$C$12:$C$215,"Rendimento",Transações!$B$12:$B$215,">="&DATE(Início!$L$10,$B19,1),Transações!$B$12:$B$215,"<"&EDATE(DATE(Início!$L$10,$B19,1),1)) -> 0 | E19: =SUMIFS(Transações!$F$12:$F$215,Transações!$C$12:$C$215,"Despesa dedutível",Transações!$B$12:$B$215,">="&DATE(Início!$L$10,$B19,1),Transações!$B$12:$B$215,"<"&EDATE(DATE(Início!$L$10,$B19,1),1)) -> 0 | F19: =SUMIFS(Transações!$F$12:$F$215,Transações!$C$12:$C$215,"Despesa não dedutível",Transações!$B$12:$B$215,">="&DATE(Início!$L$10,$B19,1),Transações!$B$12:$B$215,"<"&EDATE(DATE(Início!$L$10,$B19,1),1)) -> 0 | G19: =D19-E19-F19 -> 0
B20: 9 | C20: Setembro | D20: =SUMIFS(Transações!$F$12:$F$215,Transações!$C$12:$C$215,"Rendimento",Transações!$B$12:$B$215,">="&DATE(Início!$L$10,$B20,1),Transações!$B$12:$B$215,"<"&EDATE(DATE(Início!$L$10,$B20,1),1)) -> 0 | E20: =SUMIFS(Transações!$F$12:$F$215,Transações!$C$12:$C$215,"Despesa dedutível",Transações!$B$12:$B$215,">="&DATE(Início!$L$10,$B20,1),Transações!$B$12:$B$215,"<"&EDATE(DATE(Início!$L$10,$B20,1),1)) -> 0 | F20: =SUMIFS(Transações!$F$12:$F$215,Transações!$C$12:$C$215,"Despesa não dedutível",Transações!$B$12:$B$215,">="&DATE(Início!$L$10,$B20,1),Transações!$B$12:$B$215,"<"&EDATE(DATE(Início!$L$10,$B20,1),1)) -> 0 | G20: =D20-E20-F20 -> 0
A21: =IFERROR(HYPERLINK("#'Relatórios'!B10","RELATÓRIOS"),"RELATÓRIOS") -> RELATÓRIOS | B21: 10 | C21: Outubro | D21: =SUMIFS(Transações!$F$12:$F$215,Transações!$C$12:$C$215,"Rendimento",Transações!$B$12:$B$215,">="&DATE(Início!$L$10,$B21,1),Transações!$B$12:$B$215,"<"&EDATE(DATE(Início!$L$10,$B21,1),1)) -> 1615 | E21: =SUMIFS(Transações!$F$12:$F$215,Transações!$C$12:$C$215,"Despesa dedutível",Transações!$B$12:$B$215,">="&DATE(Início!$L$10,$B21,1),Transações!$B$12:$B$215,"<"&EDATE(DATE(Início!$L$10,$B21,1),1)) -> 465 | F21: =SUMIFS(Transações!$F$12:$F$215,Transações!$C$12:$C$215,"Despesa não dedutível",Transações!$B$12:$B$215,">="&DATE(Início!$L$10,$B21,1),Transações!$B$12:$B$215,"<"&EDATE(DATE(Início!$L$10,$B21,1),1)) -> 0 | G21: =D21-E21-F21 -> 1150
B22: 11 | C22: Novembro | D22: =SUMIFS(Transações!$F$12:$F$215,Transações!$C$12:$C$215,"Rendimento",Transações!$B$12:$B$215,">="&DATE(Início!$L$10,$B22,1),Transações!$B$12:$B$215,"<"&EDATE(DATE(Início!$L$10,$B22,1),1)) -> 0 | E22: =SUMIFS(Transações!$F$12:$F$215,Transações!$C$12:$C$215,"Despesa dedutível",Transações!$B$12:$B$215,">="&DATE(Início!$L$10,$B22,1),Transações!$B$12:$B$215,"<"&EDATE(DATE(Início!$L$10,$B22,1),1)) -> 0 | F22: =SUMIFS(Transações!$F$12:$F$215,Transações!$C$12:$C$215,"Despesa não dedutível",Transações!$B$12:$B$215,">="&DATE(Início!$L$10,$B22,1),Transações!$B$12:$B$215,"<"&EDATE(DATE(Início!$L$10,$B22,1),1)) -> 0 | G22: =D22-E22-F22 -> 0
B23: 12 | C23: Dezembro | D23: =SUMIFS(Transações!$F$12:$F$215,Transações!$C$12:$C$215,"Rendimento",Transações!$B$12:$B$215,">="&DATE(Início!$L$10,$B23,1),Transações!$B$12:$B$215,"<"&EDATE(DATE(Início!$L$10,$B23,1),1)) -> 0 | E23: =SUMIFS(Transações!$F$12:$F$215,Transações!$C$12:$C$215,"Despesa dedutível",Transações!$B$12:$B$215,">="&DATE(Início!$L$10,$B23,1),Transações!$B$12:$B$215,"<"&EDATE(DATE(Início!$L$10,$B23,1),1)) -> 0 | F23: =SUMIFS(Transações!$F$12:$F$215,Transações!$C$12:$C$215,"Despesa não dedutível",Transações!$B$12:$B$215,">="&DATE(Início!$L$10,$B23,1),Transações!$B$12:$B$215,"<"&EDATE(DATE(Início!$L$10,$B23,1),1)) -> 0 | G23: =D23-E23-F23 -> 0
C25: TOTAL DO ANO | D25: =SUM(D12:D23) -> 1615 | E25: =SUM(E12:E23) -> 611 | F25: =SUM(F12:F23) -> 0 | G25: =SUM(G12:G23) -> 1004
A29: Mais Consultoria
A30: Organização de IR
H32: CONFERÊNCIA DOS REGISTROS
H34: Comprovantes pendentes | K34: =COUNTIF(Transações!I12:I215,"Falta comprovante")+COUNTIF(Transações!I12:I215,"Pendente") -> 1
H37: Lançamentos revisados | K37: =COUNTIF(Transações!I12:I215,"Conferido") -> 2

Sheet TABELAS
A1: BANCOS E INSTITUIÇÕES • TABELA DE APOIO | C1: TIPOS DE TRANSAÇÃO | D1: CATEGORIAS | E1: STATUS / REVISÃO | F1: ESTADO CIVIL | G1: UF
A2: 1 - Banco do Brasil | C2: Rendimento | D2: Salário | E2: Pendente | F2: Solteiro(a) | G2: AC
A3: 102 - XP Investimentos CCTVM S.A. | C3: Despesa dedutível | D3: Prestação de serviços | E3: Conferido | F3: Casado(a) | G3: AL
A4: 104 - Caixa Econômica Federal | C4: Despesa não dedutível | D4: Aposentadoria | E4: Falta comprovante | F4: Divorciado(a) | G4: AP
A5: 119 - Banco Western Union do Brasil | C5: Movimentação patrimonial | D5: Aluguel | E5: Revisar | F5: Viúvo(a) | G5: AM
A6: 184 - Banco Itaú BBA S.A. | D6: Investimentos | F6: União estável | G6: BA
A7: 197 - Stone Pagamentos | D7: Dividendos | F7: Separado(a) | G7: CE
A8: 208 - Banco BTG Pactual | D8: Saúde | G8: DF
A9: 212 - Banco Original | D9: Educação | G9: ES
A10: 218 - Banco Bonsucesso | D10: Previdência | G10: GO
A11: 229 - Banco Cruzeiro do Sul | D11: Doações | G11: MA
A12: 237 - Banco Bradesco | D12: Bens | G12: MT
A13: 24 - Banco de Pernambuco | D13: Outros | G13: MS
A14: 241 - Banco Clássico | G14: MG
A15: 250 - Banco de Crédito e Varejo (BCV) | G15: PA
A16: 260 - Nubank | G16: PB
A17: 29 - Banco do Estado do Rio de Janeiro | G17: PR
A18: 290 - PagBank | G18: PE
A19: 3 - Banco da Amazônia | G19: PI
A20: 33 - Banco Santander | G20: RJ
A21: 336 - C6 Bank | G21: RN
A22: 341 - Itaú Unibanco | G22: RS
A23: 37 - Banco do Estado do Pará | G23: RO
A24: 376 - Banco JPMorgan S.A. | G24: RR
A25: 380 - PicPay | G25: SC
... A28: 422 - Banco Safra | G28: TO
A29: 44 - Banco BVA
A30: 464 - Banco Sumitomo Mitsui Brasileiro
A31: 477 - Citibank
A32: 600 - Banco Luso Brasileiro
A33: 604 - Banco Industrial do Brasil
A34: 610 - Banco VR
A35: 62 - Hipercard Banco Múltiplo
A36: 634 - Banco Triângulo
A37: 65 - Banco Lemon
A38: 654 - Banco AJ Renner
A39: 655 - Banco Votorantim
A40: 66 - Banco Morgan Stanley
... A51: 82 - Banco Topázio
